LICENSE
MANIFEST.in
README.rst
VERSION
setup.cfg
setup.py
dependencies/dev.txt
dependencies/install.txt
dependencies/test.txt
flask_servatus/__init__.py
flask_servatus/exceptions.py
flask_servatus/fields.py
flask_servatus/files.py
flask_servatus/locks.py
flask_servatus/utils.py
flask_servatus.egg-info/PKG-INFO
flask_servatus.egg-info/SOURCES.txt
flask_servatus.egg-info/dependency_links.txt
flask_servatus.egg-info/not-zip-safe
flask_servatus.egg-info/requires.txt
flask_servatus.egg-info/top_level.txt
flask_servatus/storages/__init__.py
flask_servatus/storages/amazon_s3.py
flask_servatus/storages/s3storage.py